miose_toolkit_logger/__init__.py
miose_toolkit_logger/logger.py
miose_toolkit_logger-0.0.7.dist-info/METADATA
miose_toolkit_logger-0.0.7.dist-info/WHEEL
miose_toolkit_logger-0.0.7.dist-info/entry_points.txt
miose_toolkit_logger-0.0.7.dist-info/RECORD
