Metadata-Version: 2.1
Name: miose-toolkit-logger
Version: 0.0.7
Summary: Miose Toolkit 日志模块
Author: KroMiose
Author-email: li_xiangff@163.com
Requires-Python: >=3.8,<3.12
Classifier: Programming Language :: Python :: 3
Classifier: Programming Language :: Python :: 3.8
Classifier: Programming Language :: Python :: 3.9
Classifier: Programming Language :: Python :: 3.10
Classifier: Programming Language :: Python :: 3.11
Requires-Dist: loguru (>=0.7.0,<0.8.0)
